Workbook
Name Slicer_Branch: #N/A
Name Slicer_Channel: #N/A
Name Slicer_Employee: #N/A

Sheet Project_Brief
A1: Independent Excel Project | B1: Restaurant Sales & Performance Analysis
A2: Scenario | B2: You are a junior Data Analyst for a small restaurant business with 3 branches. Management wants a clean analysis of sales, profit, branches, employees, channels, and product performance.
A3: Your Role | B3: Work independently. Clean and validate the data, analyze it, extract business insights, give recommendations, and build an interactive dashboard.
A4: Rule 1 | B4: Do not invent missing values unless you can justify them from the existing data.
A5: Rule 2 | B5: Document the issues you find before cleaning them.
A6: Rule 3 | B6: Use formulas / PivotTables / XLOOKUP only when they solve a real analysis need.
A7: Rule 4 | B7: Do not ask for step-by-step instructions unless you are genuinely blocked. I will review your work and reasoning.
A9: Business Questions
A10: 1 | B10: What are Total Revenue, Total Cost, Total Profit, and Average Order Value?
A11: 2 | B11: Which Branch performs best and worst by Revenue and Profit? Is the answer the same when you consider Profit Margin?
A12: 3 | B12: Which Sales Channel performs best? Compare Dine-in, Delivery, and Takeaway.
A13: 4 | B13: Who is the highest-performing Employee by Revenue and Profit?
A14: 5 | B14: Which Category or Item is underperforming versus its Target Margin?
A15: 6 | B15: Find at least 3 meaningful Insights and write 2 Recommendations for management.
A16: 7 | B16: Build an interactive Dashboard with clear KPIs, charts, and useful slicers.
A18: Definition of Done
A19: ✓ | B19: Raw data audited and cleaned.
A20: ✓ | B20: Calculated fields created correctly where needed.
A21: ✓ | B21: Business questions answered with evidence.
A22: ✓ | B22: 3 Insights + 2 Recommendations written.
A23: ✓ | B23: Dashboard is readable, interactive, and management-friendly.

Sheet Branch
A3: Row Labels | B3: Revenue | C3: proft | D3: Profit Margin
A4: Amman | B4: 583.5 | C4: 213.9 | D4: =C4/B4 -> 0.36658098
A5: Irbid | B5: 367.4 | C5: 144.24 | D5: =C5/B5 -> 0.39259662
A6: Zarqa | B6: 336.6 | C6: 121.31 | D6: =C6/B6 -> 0.3603981
A7: Grand Total | B7: 1287.5 | C7: 479.45 | D7: =C7/B7 -> 0.37238835
B17: افضل فرع من حيث الإيرادات والارباح هو فرع عمان والاقل الزرقاء

Sheet Channel
A3: Row Labels | B3: proft | C3: Revenue
A4: Dine-in | B4: 172.14 | C4: 467.1
A5: Delivery | B5: 162.06 | C5: 439.8
A6: Takeaway | B6: 145.25 | C6: 380.6
A7: Grand Total | B7: 479.45 | C7: 1287.5
C17: افضل شانل هي بلمطعم Dine in

Sheet Employee
A3: Row Labels | B3: Revenue | C3: proft
A4: Ali | B4: 144.9 | C4: 53.68
A5: Lina | B5: 247.8 | C5: 88.42
A6: Mooath | B6: 232 | C6: 91.34
A7: Noor | B7: 163.2 | C7: 64.14
A8: Omar | B8: 330.2 | C8: 119.6
A9: Sara | B9: 149.4 | C9: 55.13
A10: (blank) | B10: 20 | C10: 7.14
A11: Grand Total | B11: 1287.5 | C11: 479.45
B20: افضل موظف في هده المقارنه هو عمر

Sheet Item
A3: Row Labels | B3: Sum of Revenue_JOD | C3: Sum of Target_Profit_JOD | D3: Sum of proft | E3: Actual Margin | F3: Target Margin | G3: Margin Gap
A4: Beef Burger | B4: 253 | C4: 88.55 | D4: 79.19 | E4: =D4/B4 -> 0.31300395 | F4: =C4/B4 -> 0.35 | G4: =E4-F4 -> -0.036996047
A5: Pepperoni Pizza | B5: 217 | C5: 78.12 | D5: 78.73 | E5: =D5/B5 -> 0.36281106 | F5: =C5/B5 -> 0.36 | G5: =E5-F5 -> 0.0028110599
A6: Greek Salad | B6: 168.5 | C6: 67.4 | D6: 69.65 | E6: =D6/B6 -> 0.41335312 | F6: =C6/B6 -> 0.4 | G6: =E6-F6 -> 0.013353116
A7: Chicken Pasta | B7: 145 | C7: 49.3 | D7: 49.33 | E7: =D7/B7 -> 0.3402069 | F7: =C7/B7 -> 0.34 | G7: =E7-F7 -> 0.00020689655
A8: Alfredo Pasta | B8: 137.5 | C8: 45.375 | D8: 44.25 | E8: =D8/B8 -> 0.32181818 | F8: =C8/B8 -> 0.33 | G8: =E8-F8 -> -0.0081818182 | I8: لاحظت ان قسم البرغر لم يحقق التارغيت بعد التدقيق كان صنف بيف برغر& شيكن برغر
A9: Margherita Pizza | B9: 114 | C9: 43.32 | D9: 44.35 | E9: =D9/B9 -> 0.38903509 | F9: =C9/B9 -> 0.38 | G9: =E9-F9 -> 0.0090350877
A10: Caesar Salad | B10: 79.8 | C10: 33.516 | D10: 35.23 | E10: =D10/B10 -> 0.4414787 | F10: =C10/B10 -> 0.42 | G10: =E10-F10 -> 0.021478697
A11: Soft Drink | B11: 55.2 | C11: 30.36 | D11: 33.04 | E11: =D11/B11 -> 0.59855072 | F11: =C11/B11 -> 0.55 | G11: =E11-F11 -> 0.048550725
A12: Fresh Juice | B12: 50 | C12: 24 | D12: 25.07 | E12: =D12/B12 -> 0.5014 | F12: =C12/B12 -> 0.48 | G12: =E12-F12 -> 0.0214
A13: Chicken Burger | B13: 67.5 | C13: 21.6 | D13: 20.61 | E13: =D13/B13 -> 0.30533333 | F13: =C13/B13 -> 0.32 | G13: =E13-F13 -> -0.014666667
A14: Grand Total | B14: 1287.5 | C14: 481.541 | D14: 479.45 | E14: =D14/B14 -> 0.37238835 | F14: =C14/B14 -> 0.37401243 | G14: =E14-F14 -> -0.0016240777
A18: Item | B18: Actual Margin | C18: Target Margin
A19: =A4 -> Beef Burger | B19: =E4 -> 0.31300395 | C19: =F4 -> 0.35
A20: =A5 -> Pepperoni Pizza | B20: =E5 -> 0.36281106 | C20: =F5 -> 0.36
A21: =A6 -> Greek Salad | B21: =E6 -> 0.41335312 | C21: =F6 -> 0.4
A22: =A7 -> Chicken Pasta | B22: =E7 -> 0.3402069 | C22: =F7 -> 0.34
A23: =A8 -> Alfredo Pasta | B23: =E8 -> 0.32181818 | C23: =F8 -> 0.33
A24: =A9 -> Margherita Pizza | B24: =E9 -> 0.38903509 | C24: =F9 -> 0.38
A25: =A10 -> Caesar Salad | B25: =E10 -> 0.4414787 | C25: =F10 -> 0.42
A26: =A11 -> Soft Drink | B26: =E11 -> 0.59855072 | C26: =F11 -> 0.55
A27: =A12 -> Fresh Juice | B27: =E12 -> 0.5014 | C27: =F12 -> 0.48
A28: =A13 -> Chicken Burger | B28: =E13 -> 0.30533333 | C28: =F13 -> 0.32

Sheet KPI_Summary
A3: Sum of Revenue_JOD | B3: Count of Order_ID | C3: Sum of Cost_JOD | D3: Sum of proft | E3: Average Order Value
A4: 1287.5 | B4: 90 | C4: 808.05 | D4: 479.45 | E4: =A4/B4 -> 14.305556

Sheet Raw_Data
A1: Order_ID | B1: Date | C1: Employee | D1: Branch | E1: Channel | F1: Item | G1: Units | H1: Unit_Price_JOD | I1: Revenue_JOD | J1: Cost_JOD | K1: proft | L1: Profit Margin | M1: Target_Margin | N1: Target_Profit_JOD | O1: Customer_Type | P1: Space_Check | Q1: Case_Check | R1: Missing_Check | S1: Type_Check | T1: Exact_Duplicate_Check
A2: O001 | B2: 46237 | C2: Ali | D2: Amman | E2: Dine-in | F2: Soft Drink | G2: 1 | H2: 1.2 | I2: 1.2 | J2: 0.49 | K2: =I2-J2 -> 0.71 | L2: =K2/I2 -> 0.59166667 | M2: =_xlfn.XLOOKUP(F2,Menu_Lookup!$A$2:$A$11,Menu_Lookup!$C$2:$C$11,"NOT FOUND") -> 0.55 | N2: =I2*M2 -> 0.66 | O2: New | P2: =IF(OR(C2<>TRIM(C2),D2<>TRIM(D2),E2<>TRIM(E2),F2<>TRIM(F2),O2<>TRIM(O2)),"CHECK","OK") -> OK | Q2: =IF(OR(NOT(EXACT(C2,PROPER(C2))),NOT(EXACT(D2,PROPER(D2))),AND(E2<>"",NOT(OR(EXACT(E2,"Dine-in"),EXACT(E2,"Delivery"),EXACT(E2,"Takeaway")))),NOT(EXACT(F2,PROPER(F2))),NOT(EXACT(O2,PROPER(O2)))),"CHECK","OK") -> OK | R2: =IF(COUNTBLANK(A2:O2)>0,"CHECK","OK") -> OK | S2: =IF(AND(ISNUMBER(B2),ISNUMBER(G2),ISNUMBER(H2),ISNUMBER(I2),ISNUMBER(J2)),"OK","CHECK") -> OK | T2: =IF(COUNTIFS($B$2:$B$91,B2,$C$2:$C$91,C2,$D$2:$D$91,D2,$E$2:$E$91,E2,$F$2:$F$91,F2,$G$2:$G$91,G2,$H$2:$H$91,H2,$I$2:$I$91,I2,$J$2:$J$91,J2,$K$2:$K$91,K2)>1,"CHECK","OK") -> OK
A3: O002 | B3: 46286 | C3: Ali | D3: Amman | E3: Takeaway | F3: Pepperoni Pizza | G3: 4 | H3: 7 | I3: 28 | J3: 17.76 | K3: =I3-J3 -> 10.24 | L3: =K3/I3 -> 0.36571429 | M3: =_xlfn.XLOOKUP(F3,Menu_Lookup!$A$2:$A$11,Menu_Lookup!$C$2:$C$11,"NOT FOUND") -> 0.36 | N3: =I3*M3 -> 10.08 | O3: Returning | P3: =IF(OR(C3<>TRIM(C3),D3<>TRIM(D3),E3<>TRIM(E3),F3<>TRIM(F3),O3<>TRIM(O3)),"CHECK","OK") -> OK | Q3: =IF(OR(NOT(EXACT(C3,PROPER(C3))),NOT(EXACT(D3,PROPER(D3))),AND(E3<>"",NOT(OR(EXACT(E3,"Dine-in"),EXACT(E3,"Delivery"),EXACT(E3,"Takeaway")))),NOT(EXACT(F3,PROPER(F3))),NOT(EXACT(O3,PROPER(O3)))),"CHECK","OK") -> OK | R3: =IF(COUNTBLANK(A3:O3)>0,"CHECK","OK") -> OK | S3: =IF(AND(ISNUMBER(B3),ISNUMBER(G3),ISNUMBER(H3),ISNUMBER(I3),ISNUMBER(J3)),"OK","CHECK") -> OK | T3: =IF(COUNTIFS($B$2:$B$91,B3,$C$2:$C$91,C3,$D$2:$D$91,D3,$E$2:$E$91,E3,$F$2:$F$91,F3,$G$2:$G$91,G3,$H$2:$H$91,H3,$I$2:$I$91,I3,$J$2:$J$91,J3,$K$2:$K$91,K3)>1,"CHECK","OK") -> OK
A4: O003 | B4: 46259 | C4: Ali | D4: Zarqa | E4: Delivery | F4: Soft Drink | G4: 1 | H4: 1.2 | I4: 1.2 | J4: 0.51 | K4: =I4-J4 -> 0.69 | L4: =K4/I4 -> 0.575 | M4: =_xlfn.XLOOKUP(F4,Menu_Lookup!$A$2:$A$11,Menu_Lookup!$C$2:$C$11,"NOT FOUND") -> 0.55 | N4: =I4*M4 -> 0.66 | O4: Returning | P4: =IF(OR(C4<>TRIM(C4),D4<>TRIM(D4),E4<>TRIM(E4),F4<>TRIM(F4),O4<>TRIM(O4)),"CHECK","OK") -> OK | Q4: =IF(OR(NOT(EXACT(C4,PROPER(C4))),NOT(EXACT(D4,PROPER(D4))),AND(E4<>"",NOT(OR(EXACT(E4,"Dine-in"),EXACT(E4,"Delivery"),EXACT(E4,"Takeaway")))),NOT(EXACT(F4,PROPER(F4))),NOT(EXACT(O4,PROPER(O4)))),"CHECK","OK") -> OK | R4: =IF(COUNTBLANK(A4:O4)>0,"CHECK","OK") -> OK | S4: =IF(AND(ISNUMBER(B4),ISNUMBER(G4),ISNUMBER(H4),ISNUMBER(I4),ISNUMBER(J4)),"OK","CHECK") -> OK | T4: =IF(COUNTIFS($B$2:$B$91,B4,$C$2:$C$91,C4,$D$2:$D$91,D4,$E$2:$E$91,E4,$F$2:$F$91,F4,$G$2:$G$91,G4,$H$2:$H$91,H4,$I$2:$I$91,I4,$J$2:$J$91,J4,$K$2:$K$91,K4)>1,"CHECK","OK") -> OK
A5: O004 | B5: 46266 | C5: Ali | D5: Zarqa | E5: Dine-in | F5: Fresh Juice | G5: 1 | H5: 2.5 | I5: 2.5 | J5: 1.2 | K5: =I5-J5 -> 1.3 | L5: =K5/I5 -> 0.52 | M5: =_xlfn.XLOOKUP(F5,Menu_Lookup!$A$2:$A$11,Menu_Lookup!$C$2:$C$11,"NOT FOUND") -> 0.48 | N5: =I5*M5 -> 1.2 | O5: New | P5: =IF(OR(C5<>TRIM(C5),D5<>TRIM(D5),E5<>TRIM(E5),F5<>TRIM(F5),O5<>TRIM(O5)),"CHECK","OK") -> OK | Q5: =IF(OR(NOT(EXACT(C5,PROPER(C5))),NOT(EXACT(D5,PROPER(D5))),AND(E5<>"",NOT(OR(EXACT(E5,"Dine-in"),EXACT(E5,"Delivery"),EXACT(E5,"Takeaway")))),NOT(EXACT(F5,PROPER(F5))),NOT(EXACT(O5,PROPER(O5)))),"CHECK","OK") -> OK | R5: =IF(COUNTBLANK(A5:O5)>0,"CHECK","OK") -> OK | S5: =IF(AND(ISNUMBER(B5),ISNUMBER(G5),ISNUMBER(H5),ISNUMBER(I5),ISNUMBER(J5)),"OK","CHECK") -> OK | T5: =IF(COUNTIFS($B$2:$B$91,B5,$C$2:$C$91,C5,$D$2:$D$91,D5,$E$2:$E$91,E5,$F$2:$F$91,F5,$G$2:$G$91,G5,$H$2:$H$91,H5,$I$2:$I$91,I5,$J$2:$J$91,J5,$K$2:$K$91,K5)>1,"CHECK","OK") -> OK
A6: O005 | B6: 46256 | C6: Ali | D6: Zarqa | E6: Takeaway | F6: Beef Burger | G6: 2 | H6: 5.5 | I6: 11 | J6: 7.44 | K6: =I6-J6 -> 3.56 | L6: =K6/I6 -> 0.32363636 | M6: =_xlfn.XLOOKUP(F6,Menu_Lookup!$A$2:$A$11,Menu_Lookup!$C$2:$C$11,"NOT FOUND") -> 0.35 | N6: =I6*M6 -> 3.85 | O6: New | P6: =IF(OR(C6<>TRIM(C6),D6<>TRIM(D6),E6<>TRIM(E6),F6<>TRIM(F6),O6<>TRIM(O6)),"CHECK","OK") -> OK | Q6: =IF(OR(NOT(EXACT(C6,PROPER(C6))),NOT(EXACT(D6,PROPER(D6))),AND(E6<>"",NOT(OR(EXACT(E6,"Dine-in"),EXACT(E6,"Delivery"),EXACT(E6,"Takeaway")))),NOT(EXACT(F6,PROPER(F6))),NOT(EXACT(O6,PROPER(O6)))),"CHECK","OK") -> OK | R6: =IF(COUNTBLANK(A6:O6)>0,"CHECK","OK") -> OK | S6: =IF(AND(ISNUMBER(B6),ISNUMBER(G6),ISNUMBER(H6),ISNUMBER(I6),ISNUMBER(J6)),"OK","CHECK") -> OK | T6: =IF(COUNTIFS($B$2:$B$91,B6,$C$2:$C$91,C6,$D$2:$D$91,D6,$E$2:$E$91,E6,$F$2:$F$91,F6,$G$2:$G$91,G6,$H$2:$H$91,H6,$I$2:$I$91,I6,$J$2:$J$91,J6,$K$2:$K$91,K6)>1,"CHECK","OK") -> OK
A7: O006 | B7: 46286 | C7: Ali | D7: Amman | E7: Dine-in | F7: Chicken Burger | G7: 4 | H7: 4.5 | I7: 18 | J7: 12.81 | K7: =I7-J7 -> 5.19 | L7: =K7/I7 -> 0.28833333 | M7: =_xlfn.XLOOKUP(F7,Menu_Lookup!$A$2:$A$11,Menu_Lookup!$C$2:$C$11,"NOT FOUND") -> 0.32 | N7: =I7*M7 -> 5.76 | O7: New | P7: =IF(OR(C7<>TRIM(C7),D7<>TRIM(D7),E7<>TRIM(E7),F7<>TRIM(F7),O7<>TRIM(O7)),"CHECK","OK") -> OK | Q7: =IF(OR(NOT(EXACT(C7,PROPER(C7))),NOT(EXACT(D7,PROPER(D7))),AND(E7<>"",NOT(OR(EXACT(E7,"Dine-in"),EXACT(E7,"Delivery"),EXACT(E7,"Takeaway")))),NOT(EXACT(F7,PROPER(F7))),NOT(EXACT(O7,PROPER(O7)))),"CHECK","OK") -> OK | R7: =IF(COUNTBLANK(A7:O7)>0,"CHECK","OK") -> OK | S7: =IF(AND(ISNUMBER(B7),ISNUMBER(G7),ISNUMBER(H7),ISNUMBER(I7),ISNUMBER(J7)),"OK","CHECK") -> OK | T7: =IF(COUNTIFS($B$2:$B$91,B7,$C$2:$C$91,C7,$D$2:$D$91,D7,$E$2:$E$91,E7,$F$2:$F$91,F7,$G$2:$G$91,G7,$H$2:$H$91,H7,$I$2:$I$91,I7,$J$2:$J$91,J7,$K$2:$K$91,K7)>1,"CHECK","OK") -> OK
A8: O007 | B8: 46294 | C8: Ali | D8: Amman | E8: Delivery | F8: Greek Salad | G8: 3 | H8: 4 | I8: 12 | J8: 7.22 | K8: =I8-J8 -> 4.78 | L8: =K8/I8 -> 0.39833333 | M8: =_xlfn.XLOOKUP(F8,Menu_Lookup!$A$2:$A$11,Menu_Lookup!$C$2:$C$11,"NOT FOUND") -> 0.4 | N8: =I8*M8 -> 4.8 | O8: New | P8: =IF(OR(C8<>TRIM(C8),D8<>TRIM(D8),E8<>TRIM(E8),F8<>TRIM(F8),O8<>TRIM(O8)),"CHECK","OK") -> OK | Q8: =IF(OR(NOT(EXACT(C8,PROPER(C8))),NOT(EXACT(D8,PROPER(D8))),AND(E8<>"",NOT(OR(EXACT(E8,"Dine-in"),EXACT(E8,"Delivery"),EXACT(E8,"Takeaway")))),NOT(EXACT(F8,PROPER(F8))),NOT(EXACT(O8,PROPER(O8)))),"CHECK","OK") -> OK | R8: =IF(COUNTBLANK(A8:O8)>0,"CHECK","OK") -> OK | S8: =IF(AND(ISNUMBER(B8),ISNUMBER(G8),ISNUMBER(H8),ISNUMBER(I8),ISNUMBER(J8)),"OK","CHECK") -> OK | T8: =IF(COUNTIFS($B$2:$B$91,B8,$C$2:$C$91,C8,$D$2:$D$91,D8,$E$2:$E$91,E8,$F$2:$F$91,F8,$G$2:$G$91,G8,$H$2:$H$91,H8,$I$2:$I$91,I8,$J$2:$J$91,J8,$K$2:$K$91,K8)>1,"CHECK","OK") -> OK
A9: O008 | B9: 46292 | C9: Ali | D9: Amman | E9: Takeaway | F9: Chicken Pasta | G9: 5 | H9: 5 | I9: 25 | J9: 16.49 | K9: =I9-J9 -> 8.51 | L9: =K9/I9 -> 0.3404 | M9: =_xlfn.XLOOKUP(F9,Menu_Lookup!$A$2:$A$11,Menu_Lookup!$C$2:$C$11,"NOT FOUND") -> 0.34 | N9: =I9*M9 -> 8.5 | O9: Returning | P9: =IF(OR(C9<>TRIM(C9),D9<>TRIM(D9),E9<>TRIM(E9),F9<>TRIM(F9),O9<>TRIM(O9)),"CHECK","OK") -> OK | Q9: =IF(OR(NOT(EXACT(C9,PROPER(C9))),NOT(EXACT(D9,PROPER(D9))),AND(E9<>"",NOT(OR(EXACT(E9,"Dine-in"),EXACT(E9,"Delivery"),EXACT(E9,"Takeaway")))),NOT(EXACT(F9,PROPER(F9))),NOT(EXACT(O9,PROPER(O9)))),"CHECK","OK") -> OK | R9: =IF(COUNTBLANK(A9:O9)>0,"CHECK","OK") -> OK | S9: =IF(AND(ISNUMBER(B9),ISNUMBER(G9),ISNUMBER(H9),ISNUMBER(I9),ISNUMBER(J9)),"OK","CHECK") -> OK | T9: =IF(COUNTIFS($B$2:$B$91,B9,$C$2:$C$91,C9,$D$2:$D$91,D9,$E$2:$E$91,E9,$F$2:$F$91,F9,$G$2:$G$91,G9,$H$2:$H$91,H9,$I$2:$I$91,I9,$J$2:$J$91,J9,$K$2:$K$91,K9)>1,"CHECK","OK") -> OK
A10: O009 | B10: 46270 | C10: Ali | D10: Amman | E10: Dine-in | F10: Greek Salad | G10: 5 | H10: 4 | I10: 20 | J10: 11.81 | K10: =I10-J10 -> 8.19 | L10: =K10/I10 -> 0.4095 | M10: =_xlfn.XLOOKUP(F10,Menu_Lookup!$A$2:$A$11,Menu_Lookup!$C$2:$C$11,"NOT FOUND") -> 0.4 | N10: =I10*M10 -> 8 | O10: New | P10: =IF(OR(C10<>TRIM(C10),D10<>TRIM(D10),E10<>TRIM(E10),F10<>TRIM(F10),O10<>TRIM(O10)),"CHECK","OK") -> OK | Q10: =IF(OR(NOT(EXACT(C10,PROPER(C10))),NOT(EXACT(D10,PROPER(D10))),AND(E10<>"",NOT(OR(EXACT(E10,"Dine-in"),EXACT(E10,"Delivery"),EXACT(E10,"Takeaway")))),NOT(EXACT(F10,PROPER(F10))),NOT(EXACT(O10,PROPER(O10)))),"CHECK","OK") -> OK | R10: =IF(COUNTBLANK(A10:O10)>0,"CHECK","OK") -> OK | S10: =IF(AND(ISNUMBER(B10),ISNUMBER(G10),ISNUMBER(H10),ISNUMBER(I10),ISNUMBER(J10)),"OK","CHECK") -> OK | T10: =IF(COUNTIFS($B$2:$B$91,B10,$C$2:$C$91,C10,$D$2:$D$91,D10,$E$2:$E$91,E10,$F$2:$F$91,F10,$G$2:$G$91,G10,$H$2:$H$91,H10,$I$2:$I$91,I10,$J$2:$J$91,J10,$K$2:$K$91,K10)>1,"CHECK","OK") -> OK
A11: O010 | B11: 46294 | C11: Ali | D11: Irbid | E11: Delivery | F11: Chicken Burger | G11: 3 | H11: 4.5 | I11: 13.5 | J11: 9.36 | K11: =I11-J11 -> 4.14 | L11: =K11/I11 -> 0.30666667 | M11: =_xlfn.XLOOKUP(F11,Menu_Lookup!$A$2:$A$11,Menu_Lookup!$C$2:$C$11,"NOT FOUND") -> 0.32 | N11: =I11*M11 -> 4.32 | O11: New | P11: =IF(OR(C11<>TRIM(C11),D11<>TRIM(D11),E11<>TRIM(E11),F11<>TRIM(F11),O11<>TRIM(O11)),"CHECK","OK") -> OK | Q11: =IF(OR(NOT(EXACT(C11,PROPER(C11))),NOT(EXACT(D11,PROPER(D11))),AND(E11<>"",NOT(OR(EXACT(E11,"Dine-in"),EXACT(E11,"Delivery"),EXACT(E11,"Takeaway")))),NOT(EXACT(F11,PROPER(F11))),NOT(EXACT(O11,PROPER(O11)))),"CHECK","OK") -> OK | R11: =IF(COUNTBLANK(A11:O11)>0,"CHECK","OK") -> OK | S11: =IF(AND(ISNUMBER(B11),ISNUMBER(G11),ISNUMBER(H11),ISNUMBER(I11),ISNUMBER(J11)),"OK","CHECK") -> OK | T11: =IF(COUNTIFS($B$2:$B$91,B11,$C$2:$C$91,C11,$D$2:$D$91,D11,$E$2:$E$91,E11,$F$2:$F$91,F11,$G$2:$G$91,G11,$H$2:$H$91,H11,$I$2:$I$91,I11,$J$2:$J$91,J11,$K$2:$K$91,K11)>1,"CHECK","OK") -> OK
A12: O011 | B12: 46270 | C12: Ali | D12: Irbid | E12: Delivery | F12: Fresh Juice | G12: 5 | H12: 2.5 | I12: 12.5 | J12: 6.13 | K12: =I12-J12 -> 6.37 | L12: =K12/I12 -> 0.5096 | M12: =_xlfn.XLOOKUP(F12,Menu_Lookup!$A$2:$A$11,Menu_Lookup!$C$2:$C$11,"NOT FOUND") -> 0.48 | N12: =I12*M12 -> 6 | O12: New | P12: =IF(OR(C12<>TRIM(C12),D12<>TRIM(D12),E12<>TRIM(E12),F12<>TRIM(F12),O12<>TRIM(O12)),"CHECK","OK") -> OK | Q12: =IF(OR(NOT(EXACT(C12,PROPER(C12))),NOT(EXACT(D12,PROPER(D12))),AND(E12<>"",NOT(OR(EXACT(E12,"Dine-in"),EXACT(E12,"Delivery"),EXACT(E12,"Takeaway")))),NOT(EXACT(F12,PROPER(F12))),NOT(EXACT(O12,PROPER(O12)))),"CHECK","OK") -> OK | R12: =IF(COUNTBLANK(A12:O12)>0,"CHECK","OK") -> OK | S12: =IF(AND(ISNUMBER(B12),ISNUMBER(G12),ISNUMBER(H12),ISNUMBER(I12),ISNUMBER(J12)),"OK","CHECK") -> OK | T12: =IF(COUNTIFS($B$2:$B$91,B12,$C$2:$C$91,C12,$D$2:$D$91,D12,$E$2:$E$91,E12,$F$2:$F$91,F12,$G$2:$G$91,G12,$H$2:$H$91,H12,$I$2:$I$91,I12,$J$2:$J$91,J12,$K$2:$K$91,K12)>1,"CHECK","OK") -> OK
A13: O012 | B13: 46250 | C13: Lina | D13: Amman | E13: Takeaway | F13: Beef Burger | G13: 1 | H13: 5.5 | I13: 5.5 | J13: 3.86 | K13: =I13-J13 -> 1.64 | L13: =K13/I13 -> 0.29818182 | M13: =_xlfn.XLOOKUP(F13,Menu_Lookup!$A$2:$A$11,Menu_Lookup!$C$2:$C$11,"NOT FOUND") -> 0.35 | N13: =I13*M13 -> 1.925 | O13: New | P13: =IF(OR(C13<>TRIM(C13),D13<>TRIM(D13),E13<>TRIM(E13),F13<>TRIM(F13),O13<>TRIM(O13)),"CHECK","OK") -> OK | Q13: =IF(OR(NOT(EXACT(C13,PROPER(C13))),NOT(EXACT(D13,PROPER(D13))),AND(E13<>"",NOT(OR(EXACT(E13,"Dine-in"),EXACT(E13,"Delivery"),EXACT(E13,"Takeaway")))),NOT(EXACT(F13,PROPER(F13))),NOT(EXACT(O13,PROPER(O13)))),"CHECK","OK") -> OK | R13: =IF(COUNTBLANK(A13:O13)>0,"CHECK","OK") -> OK | S13: =IF(AND(ISNUMBER(B13),ISNUMBER(G13),ISNUMBER(H13),ISNUMBER(I13),ISNUMBER(J13)),"OK","CHECK") -> OK | T13: =IF(COUNTIFS($B$2:$B$91,B13,$C$2:$C$91,C13,$D$2:$D$91,D13,$E$2:$E$91,E13,$F$2:$F$91,F13,$G$2:$G$91,G13,$H$2:$H$91,H13,$I$2:$I$91,I13,$J$2:$J$91,J13,$K$2:$K$91,K13)>1,"CHECK","OK") -> OK
... A90: O090 | B90: 46290 | C90: Sara | D90: Amman | E90: Dine-in | F90: Beef Burger | G90: 6 | H90: 5.5 | I90: 33 | J90: 22.65 | K90: =I90-J90 -> 10.35 | L90: =K90/I90 -> 0.31363636 | M90: =_xlfn.XLOOKUP(F90,Menu_Lookup!$A$2:$A$11,Menu_Lookup!$C$2:$C$11,"NOT FOUND") -> 0.35 | N90: =I90*M90 -> 11.55 | O90: Returning | P90: =IF(OR(C90<>TRIM(C90),D90<>TRIM(D90),E90<>TRIM(E90),F90<>TRIM(F90),O90<>TRIM(O90)),"CHECK","OK") -> OK | Q90: =IF(OR(NOT(EXACT(C90,PROPER(C90))),NOT(EXACT(D90,PROPER(D90))),AND(E90<>"",NOT(OR(EXACT(E90,"Dine-in"),EXACT(E90,"Delivery"),EXACT(E90,"Takeaway")))),NOT(EXACT(F90,PROPER(F90))),NOT(EXACT(O90,PROPER(O90)))),"CHECK","OK") -> OK | R90: =IF(COUNTBLANK(A90:O90)>0,"CHECK","OK") -> OK | S90: =IF(AND(ISNUMBER(B90),ISNUMBER(G90),ISNUMBER(H90),ISNUMBER(I90),ISNUMBER(J90)),"OK","CHECK") -> OK | T90: =IF(COUNTIFS($B$2:$B$91,B90,$C$2:$C$91,C90,$D$2:$D$91,D90,$E$2:$E$91,E90,$F$2:$F$91,F90,$G$2:$G$91,G90,$H$2:$H$91,H90,$I$2:$I$91,I90,$J$2:$J$91,J90,$K$2:$K$91,K90)>1,"CHECK","OK") -> OK
A91: O091 | B91: 46235 | D91: Zarqa | E91: Delivery | F91: Chicken Pasta | G91: 4 | H91: 5 | I91: 20 | J91: 12.86 | K91: =I91-J91 -> 7.14 | L91: =K91/I91 -> 0.357 | M91: =_xlfn.XLOOKUP(F91,Menu_Lookup!$A$2:$A$11,Menu_Lookup!$C$2:$C$11,"NOT FOUND") -> 0.34 | N91: =I91*M91 -> 6.8 | O91: New | P91: =IF(OR(C91<>TRIM(C91),D91<>TRIM(D91),E91<>TRIM(E91),F91<>TRIM(F91),O91<>TRIM(O91)),"CHECK","OK") -> OK | Q91: =IF(OR(NOT(EXACT(C91,PROPER(C91))),NOT(EXACT(D91,PROPER(D91))),AND(E91<>"",NOT(OR(EXACT(E91,"Dine-in"),EXACT(E91,"Delivery"),EXACT(E91,"Takeaway")))),NOT(EXACT(F91,PROPER(F91))),NOT(EXACT(O91,PROPER(O91)))),"CHECK","OK") -> OK | R91: =IF(COUNTBLANK(A91:O91)>0,"CHECK","OK") -> CHECK | S91: =IF(AND(ISNUMBER(B91),ISNUMBER(G91),ISNUMBER(H91),ISNUMBER(I91),ISNUMBER(J91)),"OK","CHECK") -> OK | T91: =IF(COUNTIFS($B$2:$B$91,B91,$C$2:$C$91,C91,$D$2:$D$91,D91,$E$2:$E$91,E91,$F$2:$F$91,F91,$G$2:$G$91,G91,$H$2:$H$91,H91,$I$2:$I$91,I91,$J$2:$J$91,J91,$K$2:$K$91,K91)>1,"CHECK","OK") -> OK
A92: Total | H92: =SUBTOTAL(109,RestaurantSales[Unit_Price_JOD]) -> 385.5 | I92: =SUBTOTAL(101,RestaurantSales[Revenue_JOD]) -> 14.305556 | J92: =SUBTOTAL(101,RestaurantSales[Cost_JOD]) -> 8.9783333 | K92: =SUBTOTAL(109,RestaurantSales[proft]) -> 479.45 | N92: =SUBTOTAL(109,RestaurantSales[Target_Profit_JOD]) -> 481.541

Sheet noots
A1: تم
C12: تم حدف صف O092 لانه سجل شاد بشكل ملحوظ سوفت درينك بطبيعه سعرها 1.20 هنا مختلفه 4.14 بوحدت 3.854945055
E15: أوصي بمراجعة وتدقيق سجل Greek Salad الذي ظهر بسعر 5.50 JOD والتأكد من المصدر الأصلي، لأنه مختلف عن السعر المعتاد 4.00 JOD، بدون تعديل القيمة قبل التحقق
I21: افضل فرع من حيث الإيرادات والارباح هو فرع عمان والاقل الزرقاء
L22: افضل شانل هي بلمطعم Dine in
K23: افضل موظف في هده المقارنه هو عمر
H24: لاحظت ان قسم البرغر لم يحقق التارغيت بعد التدقيق كان صنف بيف برغر& شيكن برغر

Sheet Dashboard
H1: Restaurant Sales Performance Dashboard
B3: Total Cost | F3: Total Revenue | J3: Total Profit | N3: Average Order Value
B4: =GETPIVOTDATA("Sum of Cost_JOD",KPI_Summary!$A$3) -> 808.05 | F4: =GETPIVOTDATA("Sum of Revenue_JOD",KPI_Summary!$A$3) -> 1287.5 | J4: =GETPIVOTDATA("Sum of proft",KPI_Summary!$A$3) -> 479.45 | N4: =KPI_Summary!E4 -> 14.305556

Sheet Menu_Lookup
A1: Item | B1: Category | C1: Target_Margin
A2: Chicken Burger | B2: Burgers | C2: 0.32
A3: Alfredo Pasta | B3: Pasta | C3: 0.33
A4: Chicken Pasta | B4: Pasta | C4: 0.34
A5: Beef Burger | B5: Burgers | C5: 0.35
A6: Pepperoni Pizza | B6: Pizza | C6: 0.36
A7: Margherita Pizza | B7: Pizza | C7: 0.38
A8: Greek Salad | B8: Salads | C8: 0.4
A9: Caesar Salad | B9: Salads | C9: 0.42
A10: Fresh Juice | B10: Beverages | C10: 0.48
A11: Soft Drink | B11: Beverages | C11: 0.55
C16: ال Chicken Burgerهو اقل شيء من حيث هامش الربح
